pytest_embedded_qemu/__init__.py
pytest_embedded_qemu/app.py
pytest_embedded_qemu/dut.py
pytest_embedded_qemu/qemu.py
pytest_embedded_qemu-2.5.0.dist-info/licenses/LICENSE
pytest_embedded_qemu-2.5.0.dist-info/WHEEL
pytest_embedded_qemu-2.5.0.dist-info/METADATA
pytest_embedded_qemu-2.5.0.dist-info/RECORD
