Metadata-Version: 2.4
Name: pytest-embedded-qemu
Version: 2.5.0
Summary: Make pytest-embedded plugin work with QEMU.
Author-email: Fu Hanxi <fuhanxi@espressif.com>
Requires-Python: >=3.10
Classifier: Development Status :: 5 - Production/Stable
Classifier: Framework :: Pytest
Classifier: Intended Audience :: Developers
Classifier: License :: OSI Approved :: MIT License
Classifier: Operating System :: OS Independent
Classifier: Programming Language :: Python :: 3 :: Only
Classifier: Programming Language :: Python :: 3
Classifier: Programming Language :: Python :: 3.10
Classifier: Programming Language :: Python :: 3.11
Classifier: Programming Language :: Python :: 3.12
Classifier: Programming Language :: Python :: 3.13
Classifier: Programming Language :: Python
Classifier: Topic :: Software Development :: Testing
License-File: LICENSE
Requires-Dist: pytest-embedded~=2.5.0
Requires-Dist: qemu.qmp==0.0.3
Requires-Dist: pytest-embedded-idf~=2.5.0 ; extra == "idf"
Project-URL: changelog, https://github.com/espressif/pytest-embedded/blob/main/CHANGELOG.md
Project-URL: documentation, https://docs.espressif.com/projects/pytest-embedded/en/latest/
Project-URL: homepage, https://github.com/espressif/pytest-embedded
Project-URL: repository, https://github.com/espressif/pytest-embedded
Provides-Extra: idf
